hotspot4windows/__init__.py
hotspot4windows-1.19.3.dist-info/LICENSE
hotspot4windows-1.19.3.dist-info/METADATA
hotspot4windows-1.19.3.dist-info/WHEEL
hotspot4windows-1.19.3.dist-info/top_level.txt
hotspot4windows-1.19.3.dist-info/RECORD
