Metadata-Version: 2.1
Name: hotspot4windows
Version: 1.19.3
Summary: Wireless hotspot Python package in Windows environment.
Home-page: https://github.com/ying2002/hotspot4windows
Author: ying2002
Author-email: 877259039@qq.com
License: UNKNOWN
Platform: UNKNOWN
Classifier: Programming Language :: Python :: 3.6
Classifier: License :: OSI Approved :: MIT License
